hansken-2025.12.12.dist-info/METADATA
hansken-2025.12.12.dist-info/WHEEL
hansken-2025.12.12.dist-info/entry_points.txt
hansken-2025.12.12.dist-info/licenses/LICENSE
hansken/__init__.py
hansken/__main__.py
hansken/abstract_trace.py
hansken/admin.py
hansken/auth.py
hansken/connect.py
hansken/query.py
hansken/recipes/__init__.py
hansken/recipes/export.py
hansken/recipes/report/__init__.py
hansken/recipes/report/templates/hansken/base.html
hansken/recipes/report/templates/hansken/default.css
hansken/recipes/report/templates/hansken/macros.html
hansken/recipes/report/templates/hansken/print.css
hansken/recipes/report/templates/hansken/table.html
hansken/remote.py
hansken/tool/__init__.py
hansken/tool/_webhdfs.py
hansken/tool/command_backup.py
hansken/tool/command_export.py
hansken/tool/command_extract.py
hansken/tool/command_grant.py
hansken/tool/command_import.py
hansken/tool/command_mount.py
hansken/tool/command_quickstart.py
hansken/tool/command_shell.py
hansken/tool/command_stats.py
hansken/tool/command_tasks.py
hansken/tool/command_tools.py
hansken/tool/command_upload.py
hansken/tool/command_versions.py
hansken/trace.py
hansken/util.py
hansken-2025.12.12.dist-info/RECORD
