Metadata-Version: 2.4
Name: hansken
Version: 2025.12.12
Summary: Python API to the Hansken REST endpoint
Author-Email: Netherlands Forensic Institute <hansken-support@nfi.nl>
License-Expression: Apache-2.0
License-File: LICENSE
Requires-Python: >=3.10
Requires-Dist: decorator
Requires-Dist: ijson>=3.1
Requires-Dist: iso8601
Requires-Dist: logbook>=1.9.2
Requires-Dist: more-itertools
Requires-Dist: python-dateutil
Requires-Dist: requests>=2.7.0
Requires-Dist: requests-toolbelt>=1.0
Requires-Dist: tabulate
Provides-Extra: mount
Requires-Dist: fusepy; extra == "mount"
Provides-Extra: report
Requires-Dist: jinja2; extra == "report"
Requires-Dist: weasyprint; extra == "report"
Provides-Extra: shell
Requires-Dist: ipython; extra == "shell"
Provides-Extra: all
Requires-Dist: hansken[mount,report,shell]; extra == "all"
